clouseau/__init__.py
clouseau/inspector.py
clouseau/io_utils.py
clouseau/jax_utils.py
clouseau/torch_utils.py
clouseau-0.2.dist-info/licenses/LICENSE
clouseau-0.2.dist-info/METADATA
clouseau-0.2.dist-info/WHEEL
clouseau-0.2.dist-info/top_level.txt
clouseau-0.2.dist-info/RECORD
