Metadata-Version: 2.4
Name: clouseau
Version: 0.2
Summary: A library independent forward pass inspector for neural nets
Author-email: Axel Donath <mail@axeldonath.com>
Project-URL: Homepage, https://adonath.github.io/clouseau/
Project-URL: Repository, https://github.com/adonath/clouseau
Project-URL: Documentation, https://adonath.github.io/clouseau/
Keywords: python
Classifier: Intended Audience :: Developers
Classifier: Programming Language :: Python
Classifier: Programming Language :: Python :: 3
Classifier: Programming Language :: Python :: 3.10
Classifier: Programming Language :: Python :: 3.11
Classifier: Programming Language :: Python :: 3.12
Classifier: Programming Language :: Python :: 3.13
Classifier: Topic :: Software Development :: Libraries :: Python Modules
Requires-Python: <4.0,>=3.10
License-File: LICENSE
Requires-Dist: safetensors>=0.5.2
Requires-Dist: treescope>=0.1.8
Dynamic: license-file
